peepin.py
peepin-0.14.dist-info/DESCRIPTION.rst
peepin-0.14.dist-info/METADATA
peepin-0.14.dist-info/RECORD
peepin-0.14.dist-info/WHEEL
peepin-0.14.dist-info/entry_points.txt
peepin-0.14.dist-info/metadata.json
peepin-0.14.dist-info/top_level.txt
