Metadata-Version: 2.0
Name: peepin
Version: 0.14
Summary: Edits your requirements.txt by peep-hashing them
Home-page: https://github.com/peterbe/peepin
Author: Peter Bengtsson
Author-email: mail@peterbe.com
License: MIT
Keywords: pip,peep,repeatable,deploy,deployment,hash,install,installer
Platform: UNKNOWN
Classifier: Intended Audience :: Developers
Classifier: Intended Audience :: System Administrators
Classifier: License :: OSI Approved :: MIT License
Classifier: Programming Language :: Python :: 2
Classifier: Programming Language :: Python :: 2.6
Classifier: Programming Language :: Python :: 2.7
Classifier: Programming Language :: Python :: 3
Classifier: Topic :: Software Development :: Build Tools
Classifier: Topic :: System :: Installation/Setup
Classifier: Topic :: System :: Systems Administration
Requires-Dist: peep
